wolfsoftware/baseline_package_cli/__init__.py
wolfsoftware/baseline_package_cli/cli.py
wolfsoftware/baseline_package_cli/config.py
wolfsoftware/baseline_package_cli/exceptions.py
wolfsoftware/baseline_package_cli/globals.py
wolfsoftware/baseline_package_cli/main.py
wolfsoftware.baseline_package_cli-0.1.0.dist-info/LICENSE.md
wolfsoftware.baseline_package_cli-0.1.0.dist-info/METADATA
wolfsoftware.baseline_package_cli-0.1.0.dist-info/WHEEL
wolfsoftware.baseline_package_cli-0.1.0.dist-info/entry_points.txt
wolfsoftware.baseline_package_cli-0.1.0.dist-info/top_level.txt
wolfsoftware.baseline_package_cli-0.1.0.dist-info/RECORD
