Metadata-Version: 2.1
Name: wolfsoftware.baseline-package-cli
Version: 0.1.0
Summary: A nice description will go here
Home-page: https://github.com/GreyTeamToolbox/baseline-package-cli
Author: Wolf Software
Author-email: pypi@wolfsoftware.com
Project-URL: Source, https://github.com/GreyTeamToolbox/baseline-package-cli
Project-URL: Tracker, https://github.com/GreyTeamToolbox/baseline-package-cli/issues/
Project-URL: Documentation, https://github.com/GreyTeamToolbox/baseline-package-cli
Project-URL: Sponsor, https://github.com/sponsors/WolfSoftware
Classifier: Environment :: Console
Classifier: Intended Audience :: Developers
Classifier: Programming Language :: Python :: 3
Classifier: License :: OSI Approved :: MIT License
Classifier: Operating System :: OS Independent
Classifier: Topic :: Software Development
Requires-Python: >=3.9
License-File: LICENSE.md
Requires-Dist: setuptools ==70.0.0
Requires-Dist: wolfsoftware.notify ==0.1.0
